compoyse/ComPoYseDemo.py
compoyse/Composition.py
compoyse/Note.py
compoyse/NoteLetter.py
compoyse/Time.py
compoyse/Velocity.py
compoyse/Voice.py
compoyse/__init__.py
compoyse/midi/Beat.py
compoyse/midi/Composition.py
compoyse/midi/MIDIDataFileWriter.py
compoyse/midi/MIDIExceptions.py
compoyse/midi/MIDIUtility.py
compoyse/midi/Measure.py
compoyse/midi/Meter.py
compoyse/midi/Note.py
compoyse/midi/Rest.py
compoyse/midi/Section.py
compoyse/midi/Voice.py
compoyse/midi/__init__.py
compoyse/midi/Beat_dependencies/NoteLetter.py
compoyse/midi/Beat_dependencies/Time.py
compoyse/midi/Beat_dependencies/Velocity.py
compoyse/midi/Beat_dependencies/__init__.py
compoyse/wav/AudioClip.py
compoyse/wav/AudioDeviceInfoRetriever.py
compoyse/wav/AudioFile.py
compoyse/wav/AudioFileConverter.py
compoyse/wav/AudioPlayer.py
compoyse/wav/__init__.py
tests/TestComposition.py
tests/TestNote.py
tests/TestVoice.py
tests/__init__.py
compoyse-1.0.0.dist-info/METADATA
compoyse-1.0.0.dist-info/WHEEL
compoyse-1.0.0.dist-info/top_level.txt
compoyse-1.0.0.dist-info/RECORD
