Metadata-Version: 2.1
Name: compoyse
Version: 1.0.0
Summary: Generate music compositions
Home-page: https://github.com/charlies-world/ComPoYse
Author: Charlie's World
Author-email: charliesdotworld@gmail.com
License: MIT
Platform: UNKNOWN
Requires-Dist: pyaudio
Requires-Dist: pretty-midi
Requires-Dist: pydub
